{
  "Headers": [],
  "Blocks": [
    {
      "ForceDisableAnimator": false,
      "AnimationControllers": -4066,
      "MoveSlowerWhenInPlayerRoom": false,
      "MoveSlowerWithinTargetDistance": 20.0,
      "GlobalAnimSpeedMulti": 0.8,
      "PathMoveAnimSpeedMulti": 1.0,
      "RotationLerp": 6.0,
      "RotationLerpWhenNotMoving": 6.0,
      "BlendIntoAttackAnim": 0.15,
      "BlendIntoScreamAnim": 0.15,
      "AllowMovmentBlendOutOfPathMove": false,
      "PathMoveAnimDampTime": 0.05,
      "AllowClimbDownLadders": true,
      "LocomotionPathMove": "PathMove",
      "LocomotionHitReact": "Hitreact",
      "LocomotionDead": "Dead",
      "LocomotionShooterAttack": "ShooterAttack",
      "LocomotionScream": "Scream",
      "name": "Shadow",
      "internalEnabled": true,
      "persistentID": 21
    },
    {
      "ForceDisableAnimator": false,
      "AnimationControllers": "EnemyRunner, EnemyLow, EnemyCrawl",
      "MoveSlowerWhenInPlayerRoom": false,
      "MoveSlowerWithinTargetDistance": 20.0,
      "GlobalAnimSpeedMulti": 1.2,
      "PathMoveAnimSpeedMulti": 1.0,
      "RotationLerp": 6.0,
      "RotationLerpWhenNotMoving": 6.0,
      "BlendIntoAttackAnim": 0.15,
      "BlendIntoScreamAnim": 0.15,
      "AllowMovmentBlendOutOfPathMove": false,
      "PathMoveAnimDampTime": 0.05,
      "AllowClimbDownLadders": true,
      "LocomotionPathMove": "PathMove",
      "LocomotionHitReact": "Hitreact",
      "LocomotionDead": "Dead",
      "LocomotionShooterAttack": "ShooterAttack",
      "LocomotionScream": "Scream",
      "name": "Striker",
      "internalEnabled": true,
      "persistentID": 13
    },
    {
      "ForceDisableAnimator": false,
      "AnimationControllers": "EnemyRunner, EnemyLow",
      "MoveSlowerWhenInPlayerRoom": false,
      "MoveSlowerWithinTargetDistance": 20.0,
      "GlobalAnimSpeedMulti": 1.1,
      "PathMoveAnimSpeedMulti": 0.9,
      "RotationLerp": 6.0,
      "RotationLerpWhenNotMoving": 6.0,
      "BlendIntoAttackAnim": 0.15,
      "BlendIntoScreamAnim": 0.15,
      "AllowMovmentBlendOutOfPathMove": false,
      "PathMoveAnimDampTime": 0.05,
      "AllowClimbDownLadders": true,
      "LocomotionPathMove": "PathMove",
      "LocomotionHitReact": "Hitreact",
      "LocomotionDead": "Dead",
      "LocomotionShooterAttack": "ShooterAttack",
      "LocomotionScream": "Scream",
      "name": "Striker_Berserk",
      "internalEnabled": true,
      "persistentID": 43
    },
    {
      "ForceDisableAnimator": false,
      "AnimationControllers": "EnemyCrawlFlip, EnemyCrawl",
      "MoveSlowerWhenInPlayerRoom": false,
      "MoveSlowerWithinTargetDistance": 20.0,
      "GlobalAnimSpeedMulti": 1.5,
      "PathMoveAnimSpeedMulti": 1.7,
      "RotationLerp": 6.0,
      "RotationLerpWhenNotMoving": 6.0,
      "BlendIntoAttackAnim": 0.15,
      "BlendIntoScreamAnim": 0.15,
      "AllowMovmentBlendOutOfPathMove": false,
      "PathMoveAnimDampTime": 0.05,
      "AllowClimbDownLadders": true,
      "LocomotionPathMove": "PathMove",
      "LocomotionHitReact": "Hitreact",
      "LocomotionDead": "Dead",
      "LocomotionShooterAttack": "ShooterAttack",
      "LocomotionScream": "Scream",
      "name": "Striker_Child",
      "internalEnabled": true,
      "persistentID": 33
    },
    {
      "ForceDisableAnimator": false,
      "AnimationControllers": "EnemyCrawl",
      "MoveSlowerWhenInPlayerRoom": false,
      "MoveSlowerWithinTargetDistance": 20.0,
      "GlobalAnimSpeedMulti": 1.5,
      "PathMoveAnimSpeedMulti": 1.7,
      "RotationLerp": 6.0,
      "RotationLerpWhenNotMoving": 6.0,
      "BlendIntoAttackAnim": 0.15,
      "BlendIntoScreamAnim": 0.15,
      "AllowMovmentBlendOutOfPathMove": false,
      "PathMoveAnimDampTime": 0.05,
      "AllowClimbDownLadders": true,
      "LocomotionPathMove": "PathMove",
      "LocomotionHitReact": "Hitreact",
      "LocomotionDead": "Dead",
      "LocomotionShooterAttack": "ShooterAttack",
      "LocomotionScream": "Scream",
      "name": "Striker_Child_Nightmare",
      "internalEnabled": true,
      "persistentID": 49
    },
    {
      "ForceDisableAnimator": false,
      "AnimationControllers": "EnemyGiant",
      "MoveSlowerWhenInPlayerRoom": true,
      "MoveSlowerWithinTargetDistance": 15.0,
      "GlobalAnimSpeedMulti": 1.7,
      "PathMoveAnimSpeedMulti": 1.0,
      "RotationLerp": 1.5,
      "RotationLerpWhenNotMoving": 0.0,
      "BlendIntoAttackAnim": 0.5,
      "BlendIntoScreamAnim": 0.5,
      "AllowMovmentBlendOutOfPathMove": true,
      "PathMoveAnimDampTime": 0.4,
      "AllowClimbDownLadders": false,
      "LocomotionPathMove": "PathMove",
      "LocomotionHitReact": "Hitreact",
      "LocomotionDead": "Dead",
      "LocomotionShooterAttack": "ShooterAttack",
      "LocomotionScream": "Scream",
      "name": "Striker_Big",
      "internalEnabled": true,
      "persistentID": 16
    },
    {
      "ForceDisableAnimator": false,
      "AnimationControllers": "EnemyGiant",
      "MoveSlowerWhenInPlayerRoom": true,
      "MoveSlowerWithinTargetDistance": 15.0,
      "GlobalAnimSpeedMulti": 2.5,
      "PathMoveAnimSpeedMulti": 0.4,
      "RotationLerp": 0.6,
      "RotationLerpWhenNotMoving": 1.0,
      "BlendIntoAttackAnim": 0.5,
      "BlendIntoScreamAnim": 0.5,
      "AllowMovmentBlendOutOfPathMove": true,
      "PathMoveAnimDampTime": 0.4,
      "AllowClimbDownLadders": false,
      "LocomotionPathMove": "PathMove",
      "LocomotionHitReact": "Hitreact",
      "LocomotionDead": "Dead",
      "LocomotionShooterAttack": "ShooterAttack",
      "LocomotionScream": "Scream",
      "name": "Striker_Big_Nightmare",
      "internalEnabled": true,
      "persistentID": 48
    },
    {
      "ForceDisableAnimator": false,
      "AnimationControllers": "EnemyRunner",
      "MoveSlowerWhenInPlayerRoom": true,
      "MoveSlowerWithinTargetDistance": 23.0,
      "GlobalAnimSpeedMulti": 1.5,
      "PathMoveAnimSpeedMulti": 1.0,
      "RotationLerp": 1.5,
      "RotationLerpWhenNotMoving": 0.8,
      "BlendIntoAttackAnim": 0.5,
      "BlendIntoScreamAnim": 0.5,
      "AllowMovmentBlendOutOfPathMove": true,
      "PathMoveAnimDampTime": 0.05,
      "AllowClimbDownLadders": false,
      "LocomotionPathMove": "PathMove",
      "LocomotionHitReact": "Hitreact",
      "LocomotionDead": "Dead",
      "LocomotionShooterAttack": "ShooterAttack",
      "LocomotionScream": "Scream",
      "name": "Tank",
      "internalEnabled": true,
      "persistentID": 34
    },
    {
      "ForceDisableAnimator": false,
      "AnimationControllers": "EnemyExploder",
      "MoveSlowerWhenInPlayerRoom": true,
      "MoveSlowerWithinTargetDistance": 17.5,
      "GlobalAnimSpeedMulti": 1.4,
      "PathMoveAnimSpeedMulti": 1.0,
      "RotationLerp": 1.5,
      "RotationLerpWhenNotMoving": 0.8,
      "BlendIntoAttackAnim": 0.5,
      "BlendIntoScreamAnim": 0.5,
      "AllowMovmentBlendOutOfPathMove": true,
      "PathMoveAnimDampTime": 0.05,
      "AllowClimbDownLadders": false,
      "LocomotionPathMove": "PathMove",
      "LocomotionHitReact": "Hitreact",
      "LocomotionDead": "Dead",
      "LocomotionShooterAttack": "ShooterAttack",
      "LocomotionScream": "Scream",
      "name": "Tank_Boss",
      "internalEnabled": true,
      "persistentID": 39
    },
    {
      "ForceDisableAnimator": false,
      "AnimationControllers": "EnemyCrawl",
      "MoveSlowerWhenInPlayerRoom": false,
      "MoveSlowerWithinTargetDistance": 20.0,
      "GlobalAnimSpeedMulti": 2.0,
      "PathMoveAnimSpeedMulti": 1.0,
      "RotationLerp": 2.0,
      "RotationLerpWhenNotMoving": 0.0,
      "BlendIntoAttackAnim": 0.15,
      "BlendIntoScreamAnim": 0.15,
      "AllowMovmentBlendOutOfPathMove": false,
      "PathMoveAnimDampTime": 0.05,
      "AllowClimbDownLadders": false,
      "LocomotionPathMove": "PathMove",
      "LocomotionHitReact": "Hitreact",
      "LocomotionDead": "Dead",
      "LocomotionShooterAttack": "ShooterAttack",
      "LocomotionScream": "Scream",
      "name": "Striker_Boss",
      "internalEnabled": true,
      "persistentID": 19
    },
    {
      "ForceDisableAnimator": false,
      "AnimationControllers": "EnemyRunner",
      "MoveSlowerWhenInPlayerRoom": false,
      "MoveSlowerWithinTargetDistance": 20.0,
      "GlobalAnimSpeedMulti": 1.2,
      "PathMoveAnimSpeedMulti": 1.0,
      "RotationLerp": 6.0,
      "RotationLerpWhenNotMoving": 6.0,
      "BlendIntoAttackAnim": 0.15,
      "BlendIntoScreamAnim": 0.15,
      "AllowMovmentBlendOutOfPathMove": false,
      "PathMoveAnimDampTime": 0.05,
      "AllowClimbDownLadders": true,
      "LocomotionPathMove": "PathMove",
      "LocomotionHitReact": "Hitreact",
      "LocomotionDead": "Dead",
      "LocomotionShooterAttack": "ShooterAttack",
      "LocomotionScream": "Scream",
      "name": "Striker_Bullrush",
      "internalEnabled": true,
      "persistentID": 28
    },
    {
      "ForceDisableAnimator": false,
      "AnimationControllers": "EnemyFiddler",
      "MoveSlowerWhenInPlayerRoom": false,
      "MoveSlowerWithinTargetDistance": 20.0,
      "GlobalAnimSpeedMulti": 1.0,
      "PathMoveAnimSpeedMulti": 1.0,
      "RotationLerp": 6.0,
      "RotationLerpWhenNotMoving": 6.0,
      "BlendIntoAttackAnim": 0.15,
      "BlendIntoScreamAnim": 0.15,
      "AllowMovmentBlendOutOfPathMove": false,
      "PathMoveAnimDampTime": 0.05,
      "AllowClimbDownLadders": true,
      "LocomotionPathMove": "PathMove",
      "LocomotionHitReact": "Hitreact",
      "LocomotionDead": "Dead",
      "LocomotionShooterAttack": "ShooterAttack",
      "LocomotionScream": "Scream",
      "name": "Striker_Patrol",
      "internalEnabled": true,
      "persistentID": 29
    },
    {
      "ForceDisableAnimator": false,
      "AnimationControllers": -4054,
      "MoveSlowerWhenInPlayerRoom": false,
      "MoveSlowerWithinTargetDistance": 20.0,
      "GlobalAnimSpeedMulti": 1.05,
      "PathMoveAnimSpeedMulti": 1.0,
      "RotationLerp": 6.0,
      "RotationLerpWhenNotMoving": 6.0,
      "BlendIntoAttackAnim": 0.15,
      "BlendIntoScreamAnim": 0.15,
      "AllowMovmentBlendOutOfPathMove": false,
      "PathMoveAnimDampTime": 0.05,
      "AllowClimbDownLadders": true,
      "LocomotionPathMove": "PathMove",
      "LocomotionHitReact": "Hitreact",
      "LocomotionDead": "Dead",
      "LocomotionShooterAttack": "ShooterAttack",
      "LocomotionScream": "Scream",
      "name": "Shooter",
      "internalEnabled": true,
      "persistentID": 11
    },
    {
      "ForceDisableAnimator": false,
      "AnimationControllers": -4088,
      "MoveSlowerWhenInPlayerRoom": false,
      "MoveSlowerWithinTargetDistance": 20.0,
      "GlobalAnimSpeedMulti": 1.0,
      "PathMoveAnimSpeedMulti": 1.0,
      "RotationLerp": 6.0,
      "RotationLerpWhenNotMoving": 6.0,
      "BlendIntoAttackAnim": 0.15,
      "BlendIntoScreamAnim": 0.15,
      "AllowMovmentBlendOutOfPathMove": false,
      "PathMoveAnimDampTime": 0.05,
      "AllowClimbDownLadders": true,
      "LocomotionPathMove": "PathMove",
      "LocomotionHitReact": "Hitreact",
      "LocomotionDead": "Dead",
      "LocomotionShooterAttack": "ShooterAttack",
      "LocomotionScream": "Scream",
      "name": "Shooter_Spread",
      "internalEnabled": true,
      "persistentID": 42
    },
    {
      "ForceDisableAnimator": true,
      "AnimationControllers": -4054,
      "MoveSlowerWhenInPlayerRoom": false,
      "MoveSlowerWithinTargetDistance": 10.0,
      "GlobalAnimSpeedMulti": 1.5,
      "PathMoveAnimSpeedMulti": 1.0,
      "RotationLerp": 1.5,
      "RotationLerpWhenNotMoving": 3.0,
      "BlendIntoAttackAnim": 0.15,
      "BlendIntoScreamAnim": 0.15,
      "AllowMovmentBlendOutOfPathMove": false,
      "PathMoveAnimDampTime": 0.05,
      "AllowClimbDownLadders": false,
      "LocomotionPathMove": "PathMoveFlyer",
      "LocomotionHitReact": "HitReactFlyer",
      "LocomotionDead": "DeadFlyer",
      "LocomotionShooterAttack": "ShooterAttackFlyer",
      "LocomotionScream": "ScreamFlyer",
      "name": "Flyer",
      "internalEnabled": true,
      "persistentID": 35
    },
    {
      "ForceDisableAnimator": true,
      "AnimationControllers": -4054,
      "MoveSlowerWhenInPlayerRoom": false,
      "MoveSlowerWithinTargetDistance": 10.0,
      "GlobalAnimSpeedMulti": 1.5,
      "PathMoveAnimSpeedMulti": 1.0,
      "RotationLerp": 0.5,
      "RotationLerpWhenNotMoving": 1.0,
      "BlendIntoAttackAnim": 0.15,
      "BlendIntoScreamAnim": 0.15,
      "AllowMovmentBlendOutOfPathMove": false,
      "PathMoveAnimDampTime": 0.05,
      "AllowClimbDownLadders": false,
      "LocomotionPathMove": "PathMoveFlyer",
      "LocomotionHitReact": "HitReactFlyer",
      "LocomotionDead": "DeadFlyer",
      "LocomotionShooterAttack": "ShooterAttackFlyer",
      "LocomotionScream": "ScreamFlyer",
      "name": "Flyer_Big",
      "internalEnabled": true,
      "persistentID": 37
    },
    {
      "ForceDisableAnimator": true,
      "AnimationControllers": -4054,
      "MoveSlowerWhenInPlayerRoom": false,
      "MoveSlowerWithinTargetDistance": 10.0,
      "GlobalAnimSpeedMulti": 1.5,
      "PathMoveAnimSpeedMulti": 1.0,
      "RotationLerp": 0.01,
      "RotationLerpWhenNotMoving": 0.01,
      "BlendIntoAttackAnim": 0.15,
      "BlendIntoScreamAnim": 0.15,
      "AllowMovmentBlendOutOfPathMove": false,
      "PathMoveAnimDampTime": 0.05,
      "AllowClimbDownLadders": false,
      "LocomotionPathMove": "PathMove",
      "LocomotionHitReact": "Hitreact",
      "LocomotionDead": "DeadSquidBoss",
      "LocomotionShooterAttack": "ShooterAttackFlyer",
      "LocomotionScream": "Scream",
      "name": "SquidBossBig",
      "internalEnabled": true,
      "persistentID": 36
    },
    {
      "ForceDisableAnimator": true,
      "AnimationControllers": -4054,
      "MoveSlowerWhenInPlayerRoom": false,
      "MoveSlowerWithinTargetDistance": 10.0,
      "GlobalAnimSpeedMulti": 1.5,
      "PathMoveAnimSpeedMulti": 1.0,
      "RotationLerp": 0.25,
      "RotationLerpWhenNotMoving": 0.5,
      "BlendIntoAttackAnim": 0.15,
      "BlendIntoScreamAnim": 0.15,
      "AllowMovmentBlendOutOfPathMove": false,
      "PathMoveAnimDampTime": 0.05,
      "AllowClimbDownLadders": false,
      "LocomotionPathMove": "PathMoveFlyer",
      "LocomotionHitReact": "Hitreact",
      "LocomotionDead": "DeadSquidBoss",
      "LocomotionShooterAttack": "ShooterAttackFlyer",
      "LocomotionScream": "Scream",
      "name": "SquidBossBig_Complex",
      "internalEnabled": true,
      "persistentID": 46
    },
    {
      "ForceDisableAnimator": false,
      "AnimationControllers": "EnemyBirtherCrawlFlip",
      "MoveSlowerWhenInPlayerRoom": false,
      "MoveSlowerWithinTargetDistance": 20.0,
      "GlobalAnimSpeedMulti": 1.5,
      "PathMoveAnimSpeedMulti": 2.0,
      "RotationLerp": 2.0,
      "RotationLerpWhenNotMoving": 2.0,
      "BlendIntoAttackAnim": 0.15,
      "BlendIntoScreamAnim": 0.15,
      "AllowMovmentBlendOutOfPathMove": false,
      "PathMoveAnimDampTime": 0.05,
      "AllowClimbDownLadders": false,
      "LocomotionPathMove": "PathMove",
      "LocomotionHitReact": "Hitreact",
      "LocomotionDead": "Dead",
      "LocomotionShooterAttack": "ShooterAttack",
      "LocomotionScream": "Scream",
      "name": "Birther",
      "internalEnabled": true,
      "persistentID": 31
    },
    {
      "ForceDisableAnimator": false,
      "AnimationControllers": "EnemyBirtherCrawlFlip",
      "MoveSlowerWhenInPlayerRoom": false,
      "MoveSlowerWithinTargetDistance": 20.0,
      "GlobalAnimSpeedMulti": 1.2,
      "PathMoveAnimSpeedMulti": 2.8,
      "RotationLerp": 2.0,
      "RotationLerpWhenNotMoving": 2.0,
      "BlendIntoAttackAnim": 0.15,
      "BlendIntoScreamAnim": 0.15,
      "AllowMovmentBlendOutOfPathMove": false,
      "PathMoveAnimDampTime": 0.05,
      "AllowClimbDownLadders": false,
      "LocomotionPathMove": "PathMove",
      "LocomotionHitReact": "Hitreact",
      "LocomotionDead": "Dead",
      "LocomotionShooterAttack": "ShooterAttack",
      "LocomotionScream": "Scream",
      "name": "Birther_Boss",
      "internalEnabled": true,
      "persistentID": 32
    },
    {
      "ForceDisableAnimator": false,
      "AnimationControllers": "EnemyBirtherCrawlFlip",
      "MoveSlowerWhenInPlayerRoom": false,
      "MoveSlowerWithinTargetDistance": 20.0,
      "GlobalAnimSpeedMulti": 3.7,
      "PathMoveAnimSpeedMulti": 0.08,
      "RotationLerp": 0.95,
      "RotationLerpWhenNotMoving": 0.95,
      "BlendIntoAttackAnim": 0.15,
      "BlendIntoScreamAnim": 0.15,
      "AllowMovmentBlendOutOfPathMove": false,
      "PathMoveAnimDampTime": 0.05,
      "AllowClimbDownLadders": false,
      "LocomotionPathMove": "PathMove",
      "LocomotionHitReact": "Hitreact",
      "LocomotionDead": "Dead",
      "LocomotionShooterAttack": "ShooterAttack",
      "LocomotionScream": "Scream",
      "name": "Megamother",
      "internalEnabled": true,
      "persistentID": 45
    },
    {
      "ForceDisableAnimator": false,
      "AnimationControllers": -4086,
      "MoveSlowerWhenInPlayerRoom": false,
      "MoveSlowerWithinTargetDistance": 20.0,
      "GlobalAnimSpeedMulti": 1.1,
      "PathMoveAnimSpeedMulti": 1.0,
      "RotationLerp": 6.0,
      "RotationLerpWhenNotMoving": 6.0,
      "BlendIntoAttackAnim": 0.15,
      "BlendIntoScreamAnim": 0.15,
      "AllowMovmentBlendOutOfPathMove": false,
      "PathMoveAnimDampTime": 0.05,
      "AllowClimbDownLadders": false,
      "LocomotionPathMove": "PathMove",
      "LocomotionHitReact": "Hitreact",
      "LocomotionDead": "Dead",
      "LocomotionShooterAttack": "ShooterAttack",
      "LocomotionScream": "Scream",
      "name": "Scout",
      "internalEnabled": true,
      "persistentID": 20
    },
    {
      "ForceDisableAnimator": false,
      "AnimationControllers": -4064,
      "MoveSlowerWhenInPlayerRoom": false,
      "MoveSlowerWithinTargetDistance": 0.0,
      "GlobalAnimSpeedMulti": 1.6,
      "PathMoveAnimSpeedMulti": 1.7,
      "RotationLerp": 6.0,
      "RotationLerpWhenNotMoving": 6.0,
      "BlendIntoAttackAnim": 0.15,
      "BlendIntoScreamAnim": 0.15,
      "AllowMovmentBlendOutOfPathMove": false,
      "PathMoveAnimDampTime": 0.05,
      "AllowClimbDownLadders": false,
      "LocomotionPathMove": "PathMove",
      "LocomotionHitReact": "Hitreact",
      "LocomotionDead": "Dead",
      "LocomotionShooterAttack": "ShooterAttack",
      "LocomotionScream": "Scream",
      "name": "Scout_zoomer",
      "internalEnabled": true,
      "persistentID": 44
    },
    {
      "ForceDisableAnimator": false,
      "AnimationControllers": -4080,
      "MoveSlowerWhenInPlayerRoom": false,
      "MoveSlowerWithinTargetDistance": 20.0,
      "GlobalAnimSpeedMulti": 1.5,
      "PathMoveAnimSpeedMulti": 1.0,
      "RotationLerp": 3.0,
      "RotationLerpWhenNotMoving": 0.0,
      "BlendIntoAttackAnim": 0.4,
      "BlendIntoScreamAnim": 0.15,
      "AllowMovmentBlendOutOfPathMove": false,
      "PathMoveAnimDampTime": 0.05,
      "AllowClimbDownLadders": false,
      "LocomotionPathMove": "PathMove",
      "LocomotionHitReact": "Hitreact",
      "LocomotionDead": "Dead",
      "LocomotionShooterAttack": "ShooterAttack",
      "LocomotionScream": "Scream",
      "name": "ShooterBig_RapdiFire",
      "internalEnabled": true,
      "persistentID": 18
    },
    {
      "ForceDisableAnimator": false,
      "AnimationControllers": -4094,
      "MoveSlowerWhenInPlayerRoom": false,
      "MoveSlowerWithinTargetDistance": 20.0,
      "GlobalAnimSpeedMulti": 1.0,
      "PathMoveAnimSpeedMulti": 1.0,
      "RotationLerp": 3.0,
      "RotationLerpWhenNotMoving": 0.0,
      "BlendIntoAttackAnim": 0.15,
      "BlendIntoScreamAnim": 0.15,
      "AllowMovmentBlendOutOfPathMove": false,
      "PathMoveAnimDampTime": 0.05,
      "AllowClimbDownLadders": false,
      "LocomotionPathMove": "PathMove",
      "LocomotionHitReact": "Hitreact",
      "LocomotionDead": "Dead",
      "LocomotionShooterAttack": "ShooterAttack",
      "LocomotionScream": "Scream",
      "name": "ShooterBig",
      "internalEnabled": true,
      "persistentID": 30
    },
    {
      "ForceDisableAnimator": false,
      "AnimationControllers": "EnemyPouncer",
      "MoveSlowerWhenInPlayerRoom": false,
      "MoveSlowerWithinTargetDistance": 20.0,
      "GlobalAnimSpeedMulti": 1.2,
      "PathMoveAnimSpeedMulti": 1.0,
      "RotationLerp": 6.0,
      "RotationLerpWhenNotMoving": 6.0,
      "BlendIntoAttackAnim": 0.15,
      "BlendIntoScreamAnim": 0.15,
      "AllowMovmentBlendOutOfPathMove": false,
      "PathMoveAnimDampTime": 0.05,
      "AllowClimbDownLadders": false,
      "LocomotionPathMove": "PathMove",
      "LocomotionHitReact": "Hitreact",
      "LocomotionDead": "Dead",
      "LocomotionShooterAttack": "ShooterAttack",
      "LocomotionScream": "Scream",
      "name": "Pouncer",
      "internalEnabled": true,
      "persistentID": 38
    }
  ],
  "LastPersistentID": 49
}